<?xml version="1.0" encoding="UTF-8"?>
<FindBugsFilter>
    <!-- Spring-managed beans: storing injected dependencies is the intended pattern -->
    <Match>
        <Class name="com.mariaalpha.marketdatagateway.publisher.TickKafkaPublisher"/>
        <Bug pattern="EI_EXPOSE_REP2"/>
    </Match>
    <Match>
        <Class name="com.mariaalpha.marketdatagateway.book.OrderBookManager"/>
        <Bug pattern="EI_EXPOSE_REP2"/>
    </Match>
    <Match>
        <Class name="com.mariaalpha.marketdatagateway.grpc.BookGrpcService"/>
        <Bug pattern="EI_EXPOSE_REP2"/>
    </Match>
    <Match>
        <Class name="com.mariaalpha.marketdatagateway.repository.HistoricalBarRepository"/>
        <Bug pattern="EI_EXPOSE_REP2"/>
    </Match>
    <Match>
        <Class name="com.mariaalpha.marketdatagateway.backfill.BackfillService"/>
        <Bug pattern="EI_EXPOSE_REP2"/>
    </Match>
    <Match>
        <Class name="com.mariaalpha.marketdatagateway.backfill.BackfillRunner"/>
        <Bug pattern="EI_EXPOSE_REP2"/>
    </Match>
</FindBugsFilter>
